{
  "أبوظبي": {
    "المحافظات": [
      "أبوظبي",
      "العين",
      "الغيظة",
      "السلاعة",
      "الخرمة",
      "الشوامخ",
      "الوثبة",
      "الظفرة",
      "السلع",
      "الرميلة",
      "الشهامة",
      "السويحان",
      "العين الغربية"
    ]
  },
  "دبي": {
    "المحافظات": [
      "دبي",
      "حتا",
      "جبل علي",
      "الرويس",
      "العوير",
      "الليسيلي",
      "الحبلين",
      "القرية",
      "الحدية",
      "الشوكة",
      "الصفا",
      "السطوة"
    ]
  },
  "الشارقة": {
    "المحافظات": [
      "الشارقة",
      "كلباء",
      "الذيد",
      "دبا الحصن",
      "مليحة",
      "الحمرية",
      "البريش",
      "الحمرة",
      "الخوانيج",
      "الرميثية",
      "الزبارة",
      "الحمرة الشرقية"
    ]
  },
  "عجمان": {
    "المحافظات": [
      "عجمان"
    ]
  }
}
